nutricheck/__init__.py
nutricheck/config.py
nutricheck/core.py
nutricheck/fetch.py
nutricheck/recommender.py
nutricheck/storage.py
nutricheck/utils.py
nutrichecker-0.1.0.dist-info/licenses/LICENCE
tests/__init__.py
tests/test_core.py
tests/test_fetch.py
tests/test_recommender.py
nutrichecker-0.1.0.dist-info/METADATA
nutrichecker-0.1.0.dist-info/WHEEL
nutrichecker-0.1.0.dist-info/top_level.txt
nutrichecker-0.1.0.dist-info/RECORD
