Metadata-Version: 2.4
Name: nutrichecker
Version: 0.1.0
Summary: Library advanced nutrition analysis dan rekomendasi makanan sehat
Home-page: https://github.com/username/nutricheck
Author: Eden Simamora
Author-email: Eden Simamora <aeden6877@gmail.com>
Project-URL: Homepage, https://github.com/username/nutricheck
Requires-Python: >=3.6
License-File: LICENCE
Requires-Dist: requests
Requires-Dist: pandas
Requires-Dist: numpy
Requires-Dist: scikit-learn
Requires-Dist: matplotlib
Requires-Dist: tqdm
Requires-Dist: tinydb
Requires-Dist: python-decouple
Requires-Dist: loguru
Dynamic: author
Dynamic: home-page
Dynamic: license-file
Dynamic: requires-python
